docfind/__init__.py
docfind/cli.py
docfind/db.py
docfind/gui.py
docfind/hex_extractor.py
docfind/indexer.py
docfind/search.py
docfind/utils.py
docfind/resources/icons/README.md
docfind/resources/qss/dark_theme.qss
docfind/tests/__init__.py
docfind/tests/test_db.py
docfind/tests/test_gui_smoke.py
docfind/tests/test_indexer.py
docfind/tests/test_search.py
docfind/ui/__init__.py
docfind/ui/dialogs.py
docfind-1.1.1.dist-info/licenses/LICENSE
docfind-1.1.1.dist-info/METADATA
docfind-1.1.1.dist-info/WHEEL
docfind-1.1.1.dist-info/entry_points.txt
docfind-1.1.1.dist-info/top_level.txt
docfind-1.1.1.dist-info/RECORD
