Metadata-Version: 2.4
Name: docfind
Version: 1.1.1
Summary: A cross-platform document indexing and search tool
Home-page: https://github.com/docfind/docfind
Author: cmdeniz
Author-email: CihanMertDeniz <support@cmdeniz.dev>
License: MIT
Project-URL: Homepage, https://cmdeniz.dev
Keywords: search,indexing,documents,pdf,office,fts,full-text-search
Classifier: Development Status :: 4 - Beta
Classifier: Intended Audience :: Developers
Classifier: Intended Audience :: End Users/Desktop
Classifier: License :: OSI Approved :: MIT License
Classifier: Operating System :: OS Independent
Classifier: Programming Language :: Python :: 3
Classifier: Programming Language :: Python :: 3.8
Classifier: Programming Language :: Python :: 3.9
Classifier: Programming Language :: Python :: 3.10
Classifier: Programming Language :: Python :: 3.11
Classifier: Programming Language :: Python :: 3.12
Classifier: Topic :: Office/Business
Classifier: Topic :: Text Processing :: Indexing
Requires-Python: >=3.8
License-File: LICENSE
Requires-Dist: PyQt5>=5.15.0
Requires-Dist: pdfminer.six>=20220524
Requires-Dist: python-docx>=0.8.11
Requires-Dist: openpyxl>=3.0.0
Requires-Dist: python-pptx>=0.6.21
Requires-Dist: beautifulsoup4>=4.11.0
Requires-Dist: lxml>=4.9.0
Requires-Dist: charset-normalizer>=3.0.0
Provides-Extra: dev
Requires-Dist: pytest>=7.0.0; extra == "dev"
Requires-Dist: pytest-qt>=4.2.0; extra == "dev"
Requires-Dist: pytest-cov>=4.0.0; extra == "dev"
Dynamic: license-file
